LICENSE.txt
MANIFEST.in
README.md
setup.cfg
setup.py
dia_adfpro.egg-info/PKG-INFO
dia_adfpro.egg-info/SOURCES.txt
dia_adfpro.egg-info/dependency_links.txt
dia_adfpro.egg-info/requires.txt
dia_adfpro.egg-info/top_level.txt
diaadfpro/__init__.py
diaadfpro/adfpro/__init__.py
diaadfpro/adfpro/classify.py
diaadfpro/adfpro/configuration.py
diaadfpro/adfpro/constants.py
diaadfpro/adfpro/explain.py
diaadfpro/adfpro/feature_extract.py
diaadfpro/adfpro/feature_extractors.py
diaadfpro/adfpro/golden.py
diaadfpro/adfpro/model.py
diaadfpro/adfpro/offload.py
diaadfpro/adfpro/train.py
diaadfpro/adfpro/utils.py
diaadfpro/adfpro_ui/__init__.py
diaadfpro/adfpro_ui/constants.py
diaadfpro/adfpro_ui/ui_anomaly_plots.py
diaadfpro/adfpro_ui/ui_app.py
diaadfpro/adfpro_ui/ui_components.py
diaadfpro/adfpro_ui/ui_env_cfg.py
diaadfpro/adfpro_ui/ui_env_cfg.sample.py
diaadfpro/adfpro_ui/ui_ohlc_plots.py
diaadfpro/adfpro_ui/ui_retrain.py
diaadfpro/adfpro_ui/ui_summary_table.py