Metadata-Version: 2.1
Name: dia-adfpro
Version: 1.6.7
Summary: A Python application for anomaly detection
Home-page: https://github.com/EliLillyCo/MQIT_DIA_ADFPRO
Author: Francesco Gabbanini, Manjunath Bagewadi, Henson Tauro
Author-email: fgabbanini@yahoo.it
License: MIT
License-File: LICENSE.txt
